{
    "title": "Uploads from everyone",
    "link": "https:\/\/www.flickr.com\/photos\/",
    "description": "",
    "modified": "2019-12-08T11:31:40Z",
    "generator": "https:\/\/www.flickr.com",
    "items": [
   {
        "title": "untitled-167-5.jpg",
        "link": "https:\/\/www.flickr.com\/photos\/neiljphotographyau\/49186617833\/",
        "media": {"m":"https:\/\/live.staticflickr.com\/65535\/49186617833_bdb0765e81_m.jpg"},
        "date_taken": "2019-12-07T13:11:16-08:00",
        "description": " <p><a href=\"https:\/\/www.flickr.com\/people\/neiljphotographyau\/\">neiljphotography<\/a> posted a photo:<\/p> <p><a href=\"https:\/\/www.flickr.com\/photos\/neiljphotographyau\/49186617833\/\" title=\"untitled-167-5.jpg\"><img src=\"https:\/\/live.staticflickr.com\/65535\/49186617833_bdb0765e81_m.jpg\" width=\"240\" height=\"192\" alt=\"untitled-167-5.jpg\" \/><\/a><\/p> ",
        "published": "2019-12-08T11:31:40Z",
        "author": "nobody@flickr.com (\"neiljphotography\")",
        "author_id": "152994622@N06",
        "tags": ""
   },
   {
        "title": "Street parkrun #83",
        "link": "https:\/\/www.flickr.com\/photos\/161881112@N02\/49186618633\/",
        "media": {"m":"https:\/\/live.staticflickr.com\/65535\/49186618633_f239ce7279_m.jpg"},
        "date_taken": "2019-12-07T09:21:40-08:00",
        "description": " <p><a href=\"https:\/\/www.flickr.com\/people\/161881112@N02\/\">judybev23<\/a> posted a photo:<\/p> <p><a href=\"https:\/\/www.flickr.com\/photos\/161881112@N02\/49186618633\/\" title=\"Street parkrun #83\"><img src=\"https:\/\/live.staticflickr.com\/65535\/49186618633_f239ce7279_m.jpg\" width=\"160\" height=\"240\" alt=\"Street parkrun #83\" \/><\/a><\/p> ",
        "published": "2019-12-08T11:31:56Z",
        "author": "nobody@flickr.com (\"judybev23\")",
        "author_id": "161881112@N02",
        "tags": "83"
   },
   {
        "title": "Yo mismo",
        "link": "https:\/\/www.flickr.com\/photos\/185236959@N02\/49186618708\/",
        "media": {"m":"https:\/\/live.staticflickr.com\/65535\/49186618708_b14d0f6a08_m.jpg"},
        "date_taken": "2019-12-08T12:31:26-08:00",
        "description": " <p><a href=\"https:\/\/www.flickr.com\/people\/185236959@N02\/\">phibik45<\/a> posted a photo:<\/p> <p><a href=\"https:\/\/www.flickr.com\/photos\/185236959@N02\/49186618708\/\" title=\"Yo mismo\"><img src=\"https:\/\/live.staticflickr.com\/65535\/49186618708_b14d0f6a08_m.jpg\" width=\"180\" height=\"240\" alt=\"Yo mismo\" \/><\/a><\/p> ",
        "published": "2019-12-08T11:31:58Z",
        "author": "nobody@flickr.com (\"phibik45\")",
        "author_id": "185236959@N02",
        "tags": ""
   },
   {
        "title": "Black dick",
        "link": "https:\/\/www.flickr.com\/photos\/185953499@N08\/49186618873\/",
        "media": {"m":"https:\/\/live.staticflickr.com\/65535\/49186618873_fec64fb672_m.jpg"},
        "date_taken": "2019-09-16T12:36:48-08:00",
        "description": " <p><a href=\"https:\/\/www.flickr.com\/people\/185953499@N08\/\">rgchimie<\/a> posted a photo:<\/p> <p><a href=\"https:\/\/www.flickr.com\/photos\/185953499@N08\/49186618873\/\" title=\"Black dick\"><img src=\"https:\/\/live.staticflickr.com\/65535\/49186618873_fec64fb672_m.jpg\" width=\"138\" height=\"240\" alt=\"Black dick\" \/><\/a><\/p> ",
        "published": "2019-12-08T11:32:03Z",
        "author": "nobody@flickr.com (\"rgchimie\")",
        "author_id": "185953499@N08",
        "tags": ""
   },
   {
        "title": "Cape Fur Seal",
        "link": "https:\/\/www.flickr.com\/photos\/chlorophonia\/49186619348\/",
        "media": {"m":"https:\/\/live.staticflickr.com\/65535\/49186619348_a2bf92a0df_m.jpg"},
        "date_taken": "2019-11-05T07:35:20-08:00",
        "description": " <p><a href=\"https:\/\/www.flickr.com\/people\/chlorophonia\/\">chlorophonia<\/a> posted a photo:<\/p> <p><a href=\"https:\/\/www.flickr.com\/photos\/chlorophonia\/49186619348\/\" title=\"Cape Fur Seal\"><img src=\"https:\/\/live.staticflickr.com\/65535\/49186619348_a2bf92a0df_m.jpg\" width=\"180\" height=\"240\" alt=\"Cape Fur Seal\" \/><\/a><\/p> ",
        "published": "2019-12-08T11:32:13Z",
        "author": "nobody@flickr.com (\"chlorophonia\")",
        "author_id": "27588142@N06",
        "tags": "otariidae capefurseal brownfurseal vertebrates mammals animals carnivora animalia arctocephaluspusillus arctocephaluspusilluspusillus mammalia earedseal otariid otary walvisbay erongoregion namibia"
   },
   {
        "title": "Belenes de la Oliva instalados en la Fundaci\u00f3n Jose Fernandez con motivo de la V. Rura de los Belenes de Villaviciosa, Principado de Asturias, Espa\u00f1a.",
        "link": "https:\/\/www.flickr.com\/photos\/rayporres\/49186619478\/",
        "media": {"m":"https:\/\/live.staticflickr.com\/65535\/49186619478_17ece01b50_m.jpg"},
        "date_taken": "2019-12-04T13:33:32-08:00",
        "description": " <p><a href=\"https:\/\/www.flickr.com\/people\/rayporres\/\">RAYPORRES<\/a> posted a photo:<\/p> <p><a href=\"https:\/\/www.flickr.com\/photos\/rayporres\/49186619478\/\" title=\"Belenes de la Oliva instalados en la Fundaci\u00f3n Jose Fernandez con motivo de la V. Rura de los Belenes de Villaviciosa, Principado de Asturias, Espa\u00f1a.\"><img src=\"https:\/\/live.staticflickr.com\/65535\/49186619478_17ece01b50_m.jpg\" width=\"240\" height=\"160\" alt=\"Belenes de la Oliva instalados en la Fundaci\u00f3n Jose Fernandez con motivo de la V. Rura de los Belenes de Villaviciosa, Principado de Asturias, Espa\u00f1a.\" \/><\/a><\/p> <p>Belenes de la Oliva instalados en la Fundaci\u00f3n Jose Fernandez con motivo de la V. Rura de los Belenes de Villaviciosa, Principado de Asturias, Espa\u00f1a.<\/p>",
        "published": "2019-12-08T11:32:17Z",
        "author": "nobody@flickr.com (\"RAYPORRES\")",
        "author_id": "54166377@N06",
        "tags": "villaviciosa asturias elbelendenicolas2019 belen vrutadelosbelenes principadodeasturias navidades2019 nacimiento espa\u00f1a fundacionjosecardinfernandez"
   },
   {
        "title": "IMG_20191208_120150",
        "link": "https:\/\/www.flickr.com\/photos\/144710975@N03\/49187115436\/",
        "media": {"m":"https:\/\/live.staticflickr.com\/65535\/49187115436_831b3369ca_m.jpg"},
        "date_taken": "2019-12-08T12:01:54-08:00",
        "description": " <p><a href=\"https:\/\/www.flickr.com\/people\/144710975@N03\/\">Hot-Wheels-Papa<\/a> posted a photo:<\/p> <p><a href=\"https:\/\/www.flickr.com\/photos\/144710975@N03\/49187115436\/\" title=\"IMG_20191208_120150\"><img src=\"https:\/\/live.staticflickr.com\/65535\/49187115436_831b3369ca_m.jpg\" width=\"180\" height=\"240\" alt=\"IMG_20191208_120150\" \/><\/a><\/p> ",
        "published": "2019-12-08T11:31:28Z",
        "author": "nobody@flickr.com (\"Hot-Wheels-Papa\")",
        "author_id": "144710975@N03",
        "tags": ""
   },
   {
        "title": "Film Pendek Rohani Kristen Terbaru 2019 - Sketsa - Angan-Angan ",
        "link": "https:\/\/www.flickr.com\/photos\/182217827@N04\/49187115861\/",
        "media": {"m":"https:\/\/live.staticflickr.com\/65535\/49187115861_9d6343cacf_m.jpg"},
        "date_taken": "2019-12-08T21:31:38-08:00",
        "description": " <p><a href=\"https:\/\/www.flickr.com\/people\/182217827@N04\/\">Bambang Haryanti<\/a> posted a photo:<\/p> <p><a href=\"https:\/\/www.flickr.com\/photos\/182217827@N04\/49187115861\/\" title=\"Film Pendek Rohani Kristen Terbaru 2019 - Sketsa - Angan-Angan \"><img src=\"https:\/\/live.staticflickr.com\/65535\/49187115861_9d6343cacf_m.jpg\" width=\"240\" height=\"135\" alt=\"Film Pendek Rohani Kristen Terbaru 2019 - Sketsa - Angan-Angan \" \/><\/a><\/p> ",
        "published": "2019-12-08T11:31:38Z",
        "author": "nobody@flickr.com (\"Bambang Haryanti\")",
        "author_id": "182217827@N04",
        "tags": "filmpendekrohanikristen kisahnyatakristen"
   },
   {
        "title": "\u798f\u5ca1\u5e02 \u2223 Fukuoka City",
        "link": "https:\/\/www.flickr.com\/photos\/iyhon\/49187116091\/",
        "media": {"m":"https:\/\/live.staticflickr.com\/65535\/49187116091_78a2528e27_m.jpg"},
        "date_taken": "2018-12-14T11:43:19-08:00",
        "description": " <p><a href=\"https:\/\/www.flickr.com\/people\/iyhon\/\">Iyhon Chiu<\/a> posted a photo:<\/p> <p><a href=\"https:\/\/www.flickr.com\/photos\/iyhon\/49187116091\/\" title=\"\u798f\u5ca1\u5e02 \u2223 Fukuoka City\"><img src=\"https:\/\/live.staticflickr.com\/65535\/49187116091_78a2528e27_m.jpg\" width=\"240\" height=\"160\" alt=\"\u798f\u5ca1\u5e02 \u2223 Fukuoka City\" \/><\/a><\/p> ",
        "published": "2019-12-08T11:31:45Z",
        "author": "nobody@flickr.com (\"Iyhon Chiu\")",
        "author_id": "21930152@N06",
        "tags": ""
   },
   {
        "title": "Blue Silver Santa in the corner",
        "link": "https:\/\/www.flickr.com\/photos\/144531156@N08\/49187116131\/",
        "media": {"m":"https:\/\/live.staticflickr.com\/65535\/49187116131_687d47d86b_m.jpg"},
        "date_taken": "2019-12-07T00:41:54-08:00",
        "description": " <p><a href=\"https:\/\/www.flickr.com\/people\/144531156@N08\/\">Comfort Spring<\/a> posted a photo:<\/p> <p><a href=\"https:\/\/www.flickr.com\/photos\/144531156@N08\/49187116131\/\" title=\"Blue Silver Santa in the corner\"><img src=\"https:\/\/live.staticflickr.com\/65535\/49187116131_687d47d86b_m.jpg\" width=\"173\" height=\"240\" alt=\"Blue Silver Santa in the corner\" \/><\/a><\/p> ",
        "published": "2019-12-08T11:31:45Z",
        "author": "nobody@flickr.com (\"Comfort Spring\")",
        "author_id": "144531156@N08",
        "tags": "2019 home decor diy"
   },
   {
        "title": "Diamond Fuji Tamagawa ryukuchi -25.jpg",
        "link": "https:\/\/www.flickr.com\/photos\/43256651@N07\/49187116256\/",
        "media": {"m":"https:\/\/live.staticflickr.com\/65535\/49187116256_5b62db2c3d_m.jpg"},
        "date_taken": "2019-12-08T16:15:29-08:00",
        "description": " <p><a href=\"https:\/\/www.flickr.com\/people\/43256651@N07\/\">macmmh<\/a> posted a photo:<\/p> <p><a href=\"https:\/\/www.flickr.com\/photos\/43256651@N07\/49187116256\/\" title=\"Diamond Fuji Tamagawa ryukuchi -25.jpg\"><img src=\"https:\/\/live.staticflickr.com\/65535\/49187116256_5b62db2c3d_m.jpg\" width=\"240\" height=\"160\" alt=\"Diamond Fuji Tamagawa ryukuchi -25.jpg\" \/><\/a><\/p> ",
        "published": "2019-12-08T11:31:48Z",
        "author": "nobody@flickr.com (\"macmmh\")",
        "author_id": "43256651@N07",
        "tags": "\u5bcc\u58eb\u5c71\u3000\u30c0\u30a4\u30e4\u30e2\u30f3\u30c9\u5bcc\u58eb\u3000\u591a\u6469\u5ddd\u7dd1\u5730\u4ed8\u8fd1\u304b\u3089 \u5bcc\u58eb\u5c71\u3000\u30c0\u30a4\u30e4\u30e2\u30f3\u30c9\u5bcc\u58eb\u3000\u591a\u6469\u5ddd\u7dd1\u5730\u4ed8\u8fd1\u304b"
   },
   {
        "title": " ",
        "link": "https:\/\/www.flickr.com\/photos\/nileshkorgaokar\/49187116326\/",
        "media": {"m":"https:\/\/live.staticflickr.com\/65535\/49187116326_86d509cbca_m.jpg"},
        "date_taken": "2019-12-08T07:56:29-08:00",
        "description": " <p><a href=\"https:\/\/www.flickr.com\/people\/nileshkorgaokar\/\">Unseen Horizons<\/a> posted a photo:<\/p> <p><a href=\"https:\/\/www.flickr.com\/photos\/nileshkorgaokar\/49187116326\/\" title=\" \"><img src=\"https:\/\/live.staticflickr.com\/65535\/49187116326_86d509cbca_m.jpg\" width=\"240\" height=\"180\" alt=\" \" \/><\/a><\/p> ",
        "published": "2019-12-08T11:31:50Z",
        "author": "nobody@flickr.com (\"Unseen Horizons\")",
        "author_id": "54901499@N08",
        "tags": ""
   },
   {
        "title": "\u041a\u0440\u043e\u0441\u0441\u043e\u0432\u043a\u0438 Caman \u041a\u0440\u043e\u0441\u0441\u043e\u0432\u043a\u0438, \u043a\u0435\u0434\u044b \u043f\u043e\u0432\u0441\u0435\u0434\u043d\u0435\u0432\u043d\u044b\u0435, \u043a\u0440\u0438\u043f\u0435\u0440\u044b, \u043a\u0440\u0438\u043f\u0435\u0440\u0441\u044b, \u043a\u0440\u043e\u0441\u0441\u043e\u0432\u043a\u0438 \u043c\u0443\u0436\u0441\u043a\u0438\u0435, \u043a\u0440\u043e\u0441\u0441\u043e\u0432\u043a\u0438 \u0436\u0435\u043d\u0441\u043a\u0438\u0435, \u043a\u0435\u0434\u044b \u043c\u0443\u0436\u0441\u043a\u0438\u0435, \u043a\u0435\u0434\u044b \u0436\u0435\u043d\u0441\u043a\u0438\u0435, \u0441\u043d\u0438\u043a\u0435\u0440\u0441\u044b \u0436\u0435\u043d\u0441\u043a\u0438\u0435",
        "link": "https:\/\/www.flickr.com\/photos\/185872710@N06\/49187117451\/",
        "media": {"m":"https:\/\/live.staticflickr.com\/65535\/49187117451_f8d1ab6802_m.jpg"},
        "date_taken": "2019-12-08T03:32:16-08:00",
        "description": " <p><a href=\"https:\/\/www.flickr.com\/people\/185872710@N06\/\">WhyNotovich<\/a> posted a photo:<\/p> <p><a href=\"https:\/\/www.flickr.com\/photos\/185872710@N06\/49187117451\/\" title=\"\u041a\u0440\u043e\u0441\u0441\u043e\u0432\u043a\u0438 Caman \u041a\u0440\u043e\u0441\u0441\u043e\u0432\u043a\u0438, \u043a\u0435\u0434\u044b \u043f\u043e\u0432\u0441\u0435\u0434\u043d\u0435\u0432\u043d\u044b\u0435, \u043a\u0440\u0438\u043f\u0435\u0440\u044b, \u043a\u0440\u0438\u043f\u0435\u0440\u0441\u044b, \u043a\u0440\u043e\u0441\u0441\u043e\u0432\u043a\u0438 \u043c\u0443\u0436\u0441\u043a\u0438\u0435, \u043a\u0440\u043e\u0441\u0441\u043e\u0432\u043a\u0438 \u0436\u0435\u043d\u0441\u043a\u0438\u0435, \u043a\u0435\u0434\u044b \u043c\u0443\u0436\u0441\u043a\u0438\u0435, \u043a\u0435\u0434\u044b \u0436\u0435\u043d\u0441\u043a\u0438\u0435, \u0441\u043d\u0438\u043a\u0435\u0440\u0441\u044b \u0436\u0435\u043d\u0441\u043a\u0438\u0435\"><img src=\"https:\/\/live.staticflickr.com\/65535\/49187117451_f8d1ab6802_m.jpg\" width=\"240\" height=\"180\" alt=\"\u041a\u0440\u043e\u0441\u0441\u043e\u0432\u043a\u0438 Caman \u041a\u0440\u043e\u0441\u0441\u043e\u0432\u043a\u0438, \u043a\u0435\u0434\u044b \u043f\u043e\u0432\u0441\u0435\u0434\u043d\u0435\u0432\u043d\u044b\u0435, \u043a\u0440\u0438\u043f\u0435\u0440\u044b, \u043a\u0440\u0438\u043f\u0435\u0440\u0441\u044b, \u043a\u0440\u043e\u0441\u0441\u043e\u0432\u043a\u0438 \u043c\u0443\u0436\u0441\u043a\u0438\u0435, \u043a\u0440\u043e\u0441\u0441\u043e\u0432\u043a\u0438 \u0436\u0435\u043d\u0441\u043a\u0438\u0435, \u043a\u0435\u0434\u044b \u043c\u0443\u0436\u0441\u043a\u0438\u0435, \u043a\u0435\u0434\u044b \u0436\u0435\u043d\u0441\u043a\u0438\u0435, \u0441\u043d\u0438\u043a\u0435\u0440\u0441\u044b \u0436\u0435\u043d\u0441\u043a\u0438\u0435\" \/><\/a><\/p> <p><a href=\"https:\/\/rozetka.com.ua\/section\/krossovki\/caman\/\" rel=\"noreferrer nofollow\">\u041a\u0440\u043e\u0441\u0441\u043e\u0432\u043a\u0438 Caman \u0427\u0435\u0440\u043d\u0438\u0433\u043e\u0432<\/a><\/p>",
        "published": "2019-12-08T11:32:16Z",
        "author": "nobody@flickr.com (\"WhyNotovich\")",
        "author_id": "185872710@N06",
        "tags": ""
   },
   {
        "title": "Love Skating",
        "link": "https:\/\/www.flickr.com\/photos\/81303951@N08\/49187117456\/",
        "media": {"m":"https:\/\/live.staticflickr.com\/65535\/49187117456_a286a5bf68_m.jpg"},
        "date_taken": "2019-12-08T03:32:16-08:00",
        "description": " <p><a href=\"https:\/\/www.flickr.com\/people\/81303951@N08\/\">Mags Quetzalcoatl<\/a> posted a photo:<\/p> <p><a href=\"https:\/\/www.flickr.com\/photos\/81303951@N08\/49187117456\/\" title=\"Love Skating\"><img src=\"https:\/\/live.staticflickr.com\/65535\/49187117456_a286a5bf68_m.jpg\" width=\"240\" height=\"180\" alt=\"Love Skating\" \/><\/a><\/p> <p>my skydome<br \/> <br \/> <a href=\"http:\/\/maps.secondlife.com\/secondlife\/Hoonah\/117\/174\/2765?sourceid=slshare_photo&amp;utm_source=flickr&amp;utm_medium=photo&amp;utm_campaign=slshare\" rel=\"noreferrer nofollow\">Visit this location at Hoonah North - L$2895\/week, 2 week min, 1440 prims in Second Life<\/a><\/p>",
        "published": "2019-12-08T11:32:16Z",
        "author": "nobody@flickr.com (\"Mags Quetzalcoatl\")",
        "author_id": "81303951@N08",
        "tags": "firestorm secondlife secondlife:region=hoonah secondlife:parcel=hoonahnorthl2895week2weekmin1440prims secondlife:x=117 secondlife:y=173 secondlife:z=2765"
   },
   {
        "title": "2019.12.08 \u300cAKB48 Team TP 12\u6708\u806f\u5408\u751f\u65e5\u6703\u300d@77 O.M.G.\u6587\u5275\u4e2d\u5fc3",
        "link": "https:\/\/www.flickr.com\/photos\/akb48-taiwan-clubs\/49187310632\/",
        "media": {"m":"https:\/\/live.staticflickr.com\/65535\/49187310632_d391cb9ff0_m.jpg"},
        "date_taken": "2018-12-08T17:23:59-08:00",
        "description": " <p><a href=\"https:\/\/www.flickr.com\/people\/akb48-taiwan-clubs\/\">\u524d\u7530\u5e7b\u7fbd<\/a> posted a photo:<\/p> <p><a href=\"https:\/\/www.flickr.com\/photos\/akb48-taiwan-clubs\/49187310632\/\" title=\"2019.12.08 \u300cAKB48 Team TP 12\u6708\u806f\u5408\u751f\u65e5\u6703\u300d@77 O.M.G.\u6587\u5275\u4e2d\u5fc3\"><img src=\"https:\/\/live.staticflickr.com\/65535\/49187310632_d391cb9ff0_m.jpg\" width=\"240\" height=\"160\" alt=\"2019.12.08 \u300cAKB48 Team TP 12\u6708\u806f\u5408\u751f\u65e5\u6703\u300d@77 O.M.G.\u6587\u5275\u4e2d\u5fc3\" \/><\/a><\/p> ",
        "published": "2019-12-08T11:31:34Z",
        "author": "nobody@flickr.com (\"\u524d\u7530\u5e7b\u7fbd\")",
        "author_id": "144193527@N06",
        "tags": ""
   },
   {
        "title": "\u0c17\u0c30\u0c4d\u0c2d\u0c3f\u0c23\u0c40 \u0c38\u0c4d\u0c24\u0c4d\u0c30\u0c40\u0c32\u0c41 \u0c24\u0c40\u0c38\u0c41\u0c15\u0c4b\u0c35\u0c32\u0c38\u0c3f\u0c28 \u0c05\u0c24\u0c3f \u0c2e\u0c41\u0c16\u0c4d\u0c2f\u0c2e\u0c48\u0c28 \u0c1c\u0c3e\u0c17\u0c4d\u0c30\u0c24\u0c4d\u0c24\u0c32\u0c41 ! - The most important precautions pregnant women should take!",
        "link": "https:\/\/www.flickr.com\/photos\/185267175@N08\/49187311622\/",
        "media": {"m":"https:\/\/live.staticflickr.com\/65535\/49187311622_1892e256c5_m.jpg"},
        "date_taken": "2019-12-08T03:31:56-08:00",
        "description": " <p><a href=\"https:\/\/www.flickr.com\/people\/185267175@N08\/\">naperupriya<\/a> posted a photo:<\/p> <p><a href=\"https:\/\/www.flickr.com\/photos\/185267175@N08\/49187311622\/\" title=\"\u0c17\u0c30\u0c4d\u0c2d\u0c3f\u0c23\u0c40 \u0c38\u0c4d\u0c24\u0c4d\u0c30\u0c40\u0c32\u0c41 \u0c24\u0c40\u0c38\u0c41\u0c15\u0c4b\u0c35\u0c32\u0c38\u0c3f\u0c28 \u0c05\u0c24\u0c3f \u0c2e\u0c41\u0c16\u0c4d\u0c2f\u0c2e\u0c48\u0c28 \u0c1c\u0c3e\u0c17\u0c4d\u0c30\u0c24\u0c4d\u0c24\u0c32\u0c41 ! - The most important precautions pregnant women should take!\"><img src=\"https:\/\/live.staticflickr.com\/65535\/49187311622_1892e256c5_m.jpg\" width=\"240\" height=\"160\" alt=\"\u0c17\u0c30\u0c4d\u0c2d\u0c3f\u0c23\u0c40 \u0c38\u0c4d\u0c24\u0c4d\u0c30\u0c40\u0c32\u0c41 \u0c24\u0c40\u0c38\u0c41\u0c15\u0c4b\u0c35\u0c32\u0c38\u0c3f\u0c28 \u0c05\u0c24\u0c3f \u0c2e\u0c41\u0c16\u0c4d\u0c2f\u0c2e\u0c48\u0c28 \u0c1c\u0c3e\u0c17\u0c4d\u0c30\u0c24\u0c4d\u0c24\u0c32\u0c41 ! - The most important precautions pregnant women should take!\" \/><\/a><\/p> <p>via Blogger <a href=\"https:\/\/ift.tt\/38mZeWr\" rel=\"noreferrer nofollow\">ift.tt\/38mZeWr<\/a><\/p>",
        "published": "2019-12-08T11:31:56Z",
        "author": "nobody@flickr.com (\"naperupriya\")",
        "author_id": "185267175@N08",
        "tags": "health"
   },
   {
        "title": "Th\u1ecb tr\u01b0\u1eddng Vi\u1ec7t Nam \u201ckh\u00e1t\u201d s\u1ef1 \u0111\u1ecbnh h\u01b0\u1edbng \u201cth\u1eddi trang\u201d cho n\u1ed9i th\u1ea5t",
        "link": "https:\/\/www.flickr.com\/photos\/185562296@N03\/49187311732\/",
        "media": {"m":"https:\/\/live.staticflickr.com\/65535\/49187311732_8dab3d5607_m.jpg"},
        "date_taken": "2019-06-20T16:45:12-08:00",
        "description": " <p><a href=\"https:\/\/www.flickr.com\/people\/185562296@N03\/\">vattutop30<\/a> posted a photo:<\/p> <p><a href=\"https:\/\/www.flickr.com\/photos\/185562296@N03\/49187311732\/\" title=\"Th\u1ecb tr\u01b0\u1eddng Vi\u1ec7t Nam \u201ckh\u00e1t\u201d s\u1ef1 \u0111\u1ecbnh h\u01b0\u1edbng \u201cth\u1eddi trang\u201d cho n\u1ed9i th\u1ea5t\"><img src=\"https:\/\/live.staticflickr.com\/65535\/49187311732_8dab3d5607_m.jpg\" width=\"240\" height=\"152\" alt=\"Th\u1ecb tr\u01b0\u1eddng Vi\u1ec7t Nam \u201ckh\u00e1t\u201d s\u1ef1 \u0111\u1ecbnh h\u01b0\u1edbng \u201cth\u1eddi trang\u201d cho n\u1ed9i th\u1ea5t\" \/><\/a><\/p> <p> <a href=\"http:\/\/vattu.top\/?p=978\" rel=\"noreferrer nofollow\">vattu.top\/?p=978<\/a><\/p>",
        "published": "2019-12-08T11:31:58Z",
        "author": "nobody@flickr.com (\"vattutop30\")",
        "author_id": "185562296@N03",
        "tags": ""
   },
   {
        "title": "Wood",
        "link": "https:\/\/www.flickr.com\/photos\/158575628@N02\/49187311797\/",
        "media": {"m":"https:\/\/live.staticflickr.com\/65535\/49187311797_7940289591_m.jpg"},
        "date_taken": "2019-12-01T12:01:51-08:00",
        "description": " <p><a href=\"https:\/\/www.flickr.com\/people\/158575628@N02\/\">javitube12<\/a> posted a photo:<\/p> <p><a href=\"https:\/\/www.flickr.com\/photos\/158575628@N02\/49187311797\/\" title=\"Wood\"><img src=\"https:\/\/live.staticflickr.com\/65535\/49187311797_7940289591_m.jpg\" width=\"240\" height=\"160\" alt=\"Wood\" \/><\/a><\/p> ",
        "published": "2019-12-08T11:32:00Z",
        "author": "nobody@flickr.com (\"javitube12\")",
        "author_id": "158575628@N02",
        "tags": ""
   },
   {
        "title": "no name defined",
        "link": "https:\/\/www.flickr.com\/photos\/52533011@N05\/49187312352\/",
        "media": {"m":"https:\/\/live.staticflickr.com\/65535\/49187312352_8c2f2a8d67_m.jpg"},
        "date_taken": "2019-12-08T11:32:12-08:00",
        "description": " <p><a href=\"https:\/\/www.flickr.com\/people\/52533011@N05\/\">Go Global Gallery<\/a> posted a photo:<\/p> <p><a href=\"https:\/\/www.flickr.com\/photos\/52533011@N05\/49187312352\/\" title=\"no name defined\"><img src=\"https:\/\/live.staticflickr.com\/65535\/49187312352_8c2f2a8d67_m.jpg\" width=\"181\" height=\"240\" alt=\"no name defined\" \/><\/a><\/p> <p>no description<\/p>",
        "published": "2019-12-08T11:32:12Z",
        "author": "nobody@flickr.com (\"Go Global Gallery\")",
        "author_id": "52533011@N05",
        "tags": "test"
   },
   {
        "title": "Jingle Bell Run-299.jpg",
        "link": "https:\/\/www.flickr.com\/photos\/139968267@N03\/49187312602\/",
        "media": {"m":"https:\/\/live.staticflickr.com\/65535\/49187312602_481df31f25_m.jpg"},
        "date_taken": "2019-12-07T10:49:29-08:00",
        "description": " <p><a href=\"https:\/\/www.flickr.com\/people\/139968267@N03\/\">tdkkirby<\/a> posted a photo:<\/p> <p><a href=\"https:\/\/www.flickr.com\/photos\/139968267@N03\/49187312602\/\" title=\"Jingle Bell Run-299.jpg\"><img src=\"https:\/\/live.staticflickr.com\/65535\/49187312602_481df31f25_m.jpg\" width=\"240\" height=\"160\" alt=\"Jingle Bell Run-299.jpg\" \/><\/a><\/p> ",
        "published": "2019-12-08T11:32:17Z",
        "author": "nobody@flickr.com (\"tdkkirby\")",
        "author_id": "139968267@N03",
        "tags": ""
   }
    ]
}
